{"paths":{"0":["textures/jz_img_cjdutiao",4],"1":["fish/loading_fish51",5],"2":["fish/loading_fish52",3],"3":["textures/jz_logo_gongsi",4],"4":["textures/jz_img_dutiao",4],"5":["textures/jz_btn_guanbi",4],"6":["fish/loading_fish51",3],"7":["textures/jz_icon_shilingtishi",4],"8":["textures/jz_img_bj",4],"9":["textures/jz_icon_yichangbiao",4],"10":["textures/jz_btn_tongyi",4],"11":["dzxy_bingo_haitun",3],"12":["textures/loading_particles",4],"13":["textures/jz_img9_xiahuaxian",4],"14":["textures/jz_img_cjbg",4],"15":["textures/ziyuandi",4],"16":["textures/huahen",4],"17":["textures/jz_img_dutiaodi",4],"18":["textures/jz_img9_logodi",4],"19":["textures/loading_particles",5],"20":["textures/shengluehao",4],"21":["textures/loading_particles",3],"22":["textures/jz_btn_jujue",4],"23":["textures/bianyaan",4],"24":["textures/singleColor",4],"25":["dzxy_bingo_haitun",4],"26":["dzxy_bingo_haitun",5],"27":["textures/jz_img9_qingchuyichangdi",4],"28":["textures/chen",4],"29":["fish/loading_fish51",4],"30":["fish/loading_fish52",4],"31":["fish/loading_fish52",5],"32":["textures/jz_img_dutiaodi2",4],"33":["prefabs/PrivacyPolicy",8],"34":["textures/jz_img9_logodi",2,1],"35":["dzxy_bingo_haitun",2,1],"36":["textures/jz_img_cjbg",2,1],"37":["textures/chen",2,1],"38":["textures/jz_btn_jujue",2,1],"39":["textures/jz_btn_guanbi",2,1],"40":["textures/jz_img9_qingchuyichangdi",2,1],"41":["textures/loading_particles",2,1],"42":["common/libs/platform/hortor/HSDK.d",0],"43":["textures/jz_btn_tongyi",2,1],"44":["textures/jz_logo_gongsi",2,1],"45":["textures/jz_img9_xiahuaxian",2,1],"46":["textures/jz_img_dutiao",2,1],"47":["textures/jz_img_dutiaodi",2,1],"48":["fish/loading_fish52",2,1],"50":["materials/dustAndScratches",6],"51":["textures/singleColor",2,1],"52":["textures/huahen",2,1],"53":["textures/shengluehao",2,1],"54":["common/libs/game-defines.d",0],"55":["textures/jz_img_bj",2,1],"56":["textures/jz_icon_shilingtishi",2,1],"57":["prefabs/UserAgreement",8],"58":["textures/bianyaan",2,1],"59":["common/libs/platform/global.d",0],"60":["textures/jz_icon_yichangbiao",2,1],"61":["common/scripts/extensions/ext-d.d",0],"62":["config/gen-config",1],"63":["fish/loading_fish51",2,1],"64":["materials/dustAndScratches",7],"65":["textures/jz_img_cjdutiao",2,1],"66":["textures/jz_img_dutiaodi2",2,1],"67":["textures/ziyuandi",2,1]},"types":["cc.TextAsset","cc.JsonAsset","cc.SpriteFrame","cc.Asset","cc.Texture2D","sp.SkeletonData","cc.Material","cc.EffectAsset","cc.Prefab"],"uuids":["06meL+4atNEqIAxvrGkDb7","07/tsDUNhCX50hJEWcgpUG","0fUH9MiSVAFrfJxWXia5yW","19xh99b7lL7ovXvCrjfa6I","1c9VYAW8BApLWbique06AX","2aI/xCJjpAha0AvXvjcKMB","2aytUfvgRIs4FO28RpB0Nw","38C6hA5AVAKJ2hv7eP8VBA","39Uq/lliFKuLK0IAhOTUR0","3aCXAuiqJM85uSeDhMLj/n","5aLvYiVItNYICIEw+neWgY","613g20ty5BbbmCpSoT+0E+","65v3S707BBtINm5buTUGH5","705yr/YElPEI/gG9Kia5V+","73OMpkW4NFH4KoNUzysKjG","793TTQL51Gh6pQK7hUnMpB","8aGVOxFrxKdIgDBd8hcbGW","93MQH7M1hO3LoFjIba5i3e","94TAb16BJDLpn2pcLuh57Y","a4TASFOdNDjIpQg+vr1NX9","a4XdKCmKtI16Tk3M2sbzct","b6IZa8OUtNVa8rjOX5Pzjr","ba2IuJqk1O8YRFIoyZLzFR","bdyK/8nwZEsLla8+Ral7wE","bfcTFn/l9L6qoVjVv6ibMj","c6aGrVnotOybXsQBqPtZ9W","ca7q8W0xxHxI6coYyjuhar","d4hU9qRCBCN51e6P9/7LB+","dbujmA9FROVKtJK0Y9s8/0","e6cm2im4pHMrG2qOpEoajg","e9acPLGypGuqgpdA2mWDgL","edaN2FEytJ57RWYnxd9aME","fe9u3RFmlE3ajFKVf87LLP","0fOUaUziBJGYVn0xvAaQpy","10WB7a48NKZLOHdaNYzl9R","12dwh/Gf1HYogC0x7wMj8g","21sENcQHFPYIuHRi0HLGZI","2bQBrgPBtMoZEonr3j3fU0","305IB64lhCoqUuzeoMX7aE","36kboyYtpFi7PkQ2drD01h","3a1xBQKUhJEIMXhYnpzokn","3csrBW8eNPL621UoXn66cI","3ewhfVJPVKn4IdVcCIXlCS","42DTbnxWdBf6+qwKvIglbQ","44Np6nOfhElp6KbYgn0j2W","472Dt0u6RAZbMKgS/9Hner","4dfCUc979JBrdw/7w2cyg+","58VicZGhBK155sqrV3GFMw","5ckdn9wFJGdL6NwpqRiCoh","5fuqmr+z1LTJAMp2q3I83u","69AjfgKTBFiY586GJNrq/U","82xcm4rc5CUZJZX8uDPW27","8766UDivVJsKocxbol+D0T","89EhfBj+ROgrbPjq6nB97a","8fkuTXpS9GgrYEvu1eUfgp","9ekr2ws9tAEo8/vJcqTuov","a3U2lm5X1Cy6Yik6ufxBwd","a9TI0X7AxEVLj2J0UWIp22","aaJkwpyLVAaY3Ms2jleVIc","c129Cm+n5Hdrj5Dq0eg/gI","d4ToNJfEdMuI882//r90JK","d8lRIxH3xII5GbCFbjtujJ","dd6DanqQlPTK2DTC/9rAl9","e2CDnIL6lOcafomx3FtuGS","e4SH4sugVOcZ5KfODmMtox","f08jJAgA9D3pDrXKLTjqDW","f2OMBe5X9JgIMqapv0E3yX","f7NT2y85NAsrFkZsilv+3V","02delMVqdBD70a/HSD99FK","7a/QZLET9IDreTiBfRn2PD","a2MjXRFdtLlYQ5ouAFv/+R","ecpdLyjvZBwrvm+cedCcQy"],"scenes":{"db://assets/launcher/scenes/Launcher.fire":49},"redirect":[68,0,69,0,71,0],"deps":["internal"],"packs":{},"name":"launcher","importBase":"import","nativeBase":"native","debug":false,"isZip":false,"encrypted":true,"versions":{"import":[0,"f0473",1,"92481",33,"b1b4d",2,"b144b",34,"27812",35,"3bc0f",3,"f0473",4,"f0473",36,"60c89",5,"f0473",6,"e9562",37,"690d2",38,"70a46",39,"04e9b",7,"f0473",8,"1b193",9,"f0473",40,"0ddf7",41,"dbb16",42,"29b64",43,"84099",44,"484dc",45,"3d9ac",46,"715f8",47,"b4270",10,"f0473",48,"e8229",49,"c8380",11,"3326d",12,"f0473",50,"95ffb",13,"f0473",14,"f0473",15,"f0473",51,"1089e",52,"01d7d",53,"cb30b",16,"f0473",54,"be4ed",17,"f0473",18,"f0473",55,"28f68",70,"43d76",56,"3e8f2",19,"b6206",20,"f0473",57,"38816",58,"1e479",21,"0d4e1",22,"f0473",23,"f0473",24,"f0473",59,"c013b",25,"f0473",26,"ef1aa",60,"2ec27",27,"f0473",61,"12798",28,"45bc4",62,"6776e",63,"76761",64,"8f5e7",29,"f0473",30,"f0473",31,"5555d",65,"455f2",66,"e7d2b",67,"62e8a",32,"f0473"],"native":[0,"cd18d",1,"72fba",2,"abddd",3,"40d74",4,"eb3a9",5,"22bf7",6,"03417",7,"504b0",8,"80ff6",9,"87e58",10,"d9c91",11,"6ed08",12,"39fbe",13,"26849",14,"920c4",15,"280ef",16,"7dee2",17,"13f4b",18,"c6280",19,"184d0",20,"3d8c8",21,"f299e",22,"e3721",23,"6bb80",24,"403aa",25,"f26ee",26,"b1d7e",27,"4caec",28,"76f2a",29,"f1f4d",30,"a23b0",31,"ef96b",32,"b8355"]}}